claude_orchestrator/__init__.py
claude_orchestrator/__main__.py
claude_orchestrator/constants.py
claude_orchestrator/models.py
claude_orchestrator/orchestrator.py
claude_orchestrator/utils.py
claude_orchestrator-0.2.1.dist-info/licenses/LICENSE
claude_orchestrator-0.2.1.dist-info/METADATA
claude_orchestrator-0.2.1.dist-info/WHEEL
claude_orchestrator-0.2.1.dist-info/entry_points.txt
claude_orchestrator-0.2.1.dist-info/top_level.txt
claude_orchestrator-0.2.1.dist-info/RECORD
