Metadata-Version: 2.4
Name: claude-orchestrator
Version: 0.2.1
Summary: Orchestrate multiple Claude Code instances to work in parallel
Home-page: https://github.com/kmaurinjones/claude-orchestrator
Author: Kai Maurin-Jones
Author-email: Kai Maurin-Jones <kmaurinjones@example.com>
License-Expression: MIT
Project-URL: Homepage, https://github.com/kmaurinjones/claude-orchestrator
Project-URL: Issues, https://github.com/kmaurinjones/claude-orchestrator/issues
Keywords: claude,ai,development,orchestration,parallel
Classifier: Development Status :: 3 - Alpha
Classifier: Intended Audience :: Developers
Classifier: Topic :: Software Development :: Build Tools
Classifier: Programming Language :: Python :: 3
Classifier: Programming Language :: Python :: 3.8
Classifier: Programming Language :: Python :: 3.9
Classifier: Programming Language :: Python :: 3.10
Classifier: Programming Language :: Python :: 3.11
Classifier: Programming Language :: Python :: 3.12
Classifier: Operating System :: OS Independent
Requires-Python: >=3.8
License-File: LICENSE
Provides-Extra: dev
Requires-Dist: pytest>=7.0; extra == "dev"
Requires-Dist: pytest-cov>=3.0; extra == "dev"
Requires-Dist: black>=22.0; extra == "dev"
Requires-Dist: isort>=5.0; extra == "dev"
Requires-Dist: flake8>=4.0; extra == "dev"
Requires-Dist: mypy>=0.950; extra == "dev"
Dynamic: author
Dynamic: home-page
Dynamic: license-file
Dynamic: requires-python
